openai_rev
